StreetViewSampler/StreetViewSampler.py
StreetViewSampler/__init__.py
streetviewsampler-0.1.dist-info/LICENSE
streetviewsampler-0.1.dist-info/METADATA
streetviewsampler-0.1.dist-info/WHEEL
streetviewsampler-0.1.dist-info/top_level.txt
streetviewsampler-0.1.dist-info/RECORD
